torchao/_C.cpython-312-x86_64-linux-gnu.so
torchao/__init__.py
torchao/_eval.py
torchao/ops.py
torchao/utils.py
torchao/csrc/init.cpp
torchao/csrc/cuda/fp6_llm/fp6_linear.cu
torchao/csrc/cuda/fp6_llm/weight_quant.cu
torchao/csrc/fp6_llm/float6_e3m2.cpp
torchao/csrc/fp6_llm/fp6_llm.cpp
torchao/csrc/fp6_llm/weight_prepacking.cpp
torchao/dtypes/__init__.py
torchao/dtypes/aqt.py
torchao/dtypes/float6_e3m2.py
torchao/dtypes/nf4tensor.py
torchao/dtypes/uint4.py
torchao/kernel/__init__.py
torchao/kernel/autotuner.py
torchao/kernel/intmm.py
torchao/kernel/intmm_triton.py
torchao/prototype/__init__.py
torchao/prototype/common/__init__.py
torchao/prototype/common/profiling_tools.py
torchao/prototype/dora/__init__.py
torchao/prototype/dora/dora_layer.py
torchao/prototype/dora/dora_profile.py
torchao/prototype/dora/kernels/__init__.py
torchao/prototype/dora/kernels/common.py
torchao/prototype/dora/kernels/custom_autotune.py
torchao/prototype/dora/kernels/matmul.py
torchao/prototype/dora/kernels/smallk.py
torchao/prototype/fp8/__init__.py
torchao/prototype/fp8/splitk_gemm.py
torchao/prototype/galore/__init__.py
torchao/prototype/galore/utils.py
torchao/prototype/galore/kernels/__init__.py
torchao/prototype/galore/kernels/adam_downproj_fused.py
torchao/prototype/galore/kernels/adam_step.py
torchao/prototype/galore/kernels/custom_autotune.py
torchao/prototype/galore/kernels/matmul.py
torchao/prototype/galore/kernels/quant.py
torchao/prototype/galore/optim/__init__.py
torchao/prototype/galore/optim/galore_torch.py
torchao/prototype/hqq/__init__.py
torchao/prototype/hqq/hqq_tinygemm_linear.py
torchao/prototype/hqq/kernels.py
torchao/prototype/hqq/mixed_mm.py
torchao/prototype/mx_formats/__init__.py
torchao/prototype/mx_formats/config.py
torchao/prototype/mx_formats/constants.py
torchao/prototype/mx_formats/custom_cast.py
torchao/prototype/mx_formats/fp_format_spec.py
torchao/prototype/mx_formats/mx_linear.py
torchao_nightly-2024.5.29.dist-info/LICENSE
torchao_nightly-2024.5.29.dist-info/METADATA
torchao_nightly-2024.5.29.dist-info/WHEEL
torchao_nightly-2024.5.29.dist-info/top_level.txt
torchao_nightly-2024.5.29.dist-info/RECORD
