Metadata-Version: 2.1
Name: torchao-nightly
Version: 2024.5.29
Summary: Package for applying ao techniques to GPU models
Home-page: https://github.com/pytorch-labs/ao
License-File: LICENSE
Requires-Dist: torch
Requires-Dist: numpy
Requires-Dist: sentencepiece
Requires-Dist: packaging
Requires-Dist: expecttest
Requires-Dist: hypothesis
Provides-Extra: dev
Requires-Dist: pytest (==7.4.0) ; extra == 'dev'
Requires-Dist: unittest-xml-reporting ; extra == 'dev'
Requires-Dist: parameterized ; extra == 'dev'
Requires-Dist: packaging ; extra == 'dev'
Requires-Dist: transformers ; extra == 'dev'
Requires-Dist: bitsandbytes ; extra == 'dev'
Requires-Dist: matplotlib ; extra == 'dev'
Requires-Dist: pandas ; extra == 'dev'
Requires-Dist: fire ; extra == 'dev'
Requires-Dist: tabulate ; extra == 'dev'
Requires-Dist: ninja ; extra == 'dev'
Requires-Dist: qtorch ; extra == 'dev'
